ethina/__init__.py
ethina/base_client.py
ethina/client.py
ethina/exceptions.py
ethina/providers/__init__.py
ethina/providers/anthropic.py
ethina/providers/azure_ai.py
ethina/providers/azure_openai.py
ethina/providers/bedrock.py
ethina/providers/google.py
ethina/providers/ollama.py
ethina/providers/openai.py
ethina/providers/anthropic/__init__.py
ethina/providers/anthropic/chat.py
ethina/providers/anthropic/client.py
ethina/providers/azure_ai/__init__.py
ethina/providers/azure_ai/chat.py
ethina/providers/azure_ai/client.py
ethina/providers/azure_openai/__init__.py
ethina/providers/azure_openai/chat.py
ethina/providers/azure_openai/client.py
ethina/providers/bedrock/__init__.py
ethina/providers/bedrock/chat.py
ethina/providers/bedrock/client.py
ethina/providers/google/__init__.py
ethina/providers/google/chat.py
ethina/providers/google/client.py
ethina/providers/ollama/__init__.py
ethina/providers/ollama/chat.py
ethina/providers/ollama/client.py
ethina/providers/openai/__init__.py
ethina/providers/openai/chat.py
ethina/providers/openai/client.py
ethina/utils/__init__.py
ethina/utils/config.py
ethina/utils/helpers.py
tests/__init__.py
tests/test_base_client.py
tests/test_client.py
tests/providers/__init__.py
tests/providers/test_anthropic.py
tests/providers/test_azure_ai.py
tests/providers/test_azure_openai.py
tests/providers/test_bedrock.py
tests/providers/test_google.py
tests/providers/test_ollama.py
tests/providers/test_openai.py
ethina-0.1a0.dist-info/METADATA
ethina-0.1a0.dist-info/WHEEL
ethina-0.1a0.dist-info/top_level.txt
ethina-0.1a0.dist-info/RECORD
