Metadata-Version: 2.1
Name: ethina
Version: 0.1a0
Summary: A unified interface for interacting with various Language Model (LLM) providers
Home-page: https://github.com/kstyagi23/Ethina
Author: Kshitij S. Tyagi
Author-email: hello@brahmai.in
Classifier: Development Status :: 3 - Alpha
Classifier: Intended Audience :: Developers
Classifier: License :: OSI Approved :: MIT License
Classifier: Operating System :: OS Independent
Classifier: Programming Language :: Python :: 3
Classifier: Programming Language :: Python :: 3.7
Classifier: Programming Language :: Python :: 3.8
Classifier: Programming Language :: Python :: 3.9
Classifier: Programming Language :: Python :: 3.10
Requires-Python: >=3.7
Requires-Dist: annotated-types==0.7.0
Requires-Dist: anyio==4.4.0
Requires-Dist: certifi==2024.8.30
Requires-Dist: distro==1.9.0
Requires-Dist: h11==0.14.0
Requires-Dist: httpcore==1.0.5
Requires-Dist: httpx==0.27.2
Requires-Dist: idna==3.8
Requires-Dist: jiter==0.5.0
Requires-Dist: openai==1.43.0
Requires-Dist: pydantic==2.8.2
Requires-Dist: pydantic-core==2.20.1
Requires-Dist: sniffio==1.3.1
Requires-Dist: tqdm==4.66.5
Requires-Dist: typing-extensions==4.12.2
Provides-Extra: dev
Requires-Dist: pytest>=6.0; extra == "dev"
Requires-Dist: pytest-cov; extra == "dev"
Requires-Dist: flake8; extra == "dev"
Requires-Dist: black; extra == "dev"
